<?xml version="1.0" encoding="UTF-8"?>
<T3DataStructure>
    <meta>
        <langDisable>1</langDisable>
    </meta>
    <sheets>
        <slickslider>
            <ROOT>
                <TCEforms>
                    <sheetTitle>LLL:EXT:ws_slider/Resources/Private/Language/locallang.xlf:sheet.slick</sheetTitle>
                </TCEforms>
                <type>array</type>
                <el>
                    <settings.js.autoplay>
                        <TCEforms>
                            <label>LLL:EXT:ws_slider/Resources/Private/Language/locallang.xlf:settings.common.autoplay</label>
                            <config>
                                <type>select</type>
                                <renderType>selectSingleWithTypoScriptPlaceholder</renderType>
                                <typoscriptPath>plugin.tx_wsslider.settings.renderer.slickslider.autoplay</typoscriptPath>
                                <eval>null</eval>
                                <items type="array">
                                    <numIndex index="1" type="array">
                                        <numIndex index="0">LLL:EXT:ws_slider/Resources/Private/Language/locallang.xlf:yes</numIndex>
                                        <numIndex index="1">true</numIndex>
                                    </numIndex>
                                    <numIndex index="2" type="array">
                                        <numIndex index="0">LLL:EXT:ws_slider/Resources/Private/Language/locallang.xlf:no</numIndex>
                                        <numIndex index="1">false</numIndex>
                                    </numIndex>
                                </items>
                                <maxitems>1</maxitems>
                                <size>1</size>
                            </config>
                        </TCEforms>
                    </settings.js.autoplay>

                    <settings.js.autoplaySpeed>
                        <TCEforms>
                            <label>LLL:EXT:ws_slider/Resources/Private/Language/locallang.xlf:settings.common.autoplaySpeed</label>
                            <config>
                                <type>input</type>
                                <renderType>inputWithTypoScriptPlaceholder</renderType>
                                <typoscriptPath>plugin.tx_wsslider.settings.renderer.slick.autoplaySpeed</typoscriptPath>
                                <eval>num,trim</eval>
                            </config>
                        </TCEforms>
                    </settings.js.autoplaySpeed>
                </el>
            </ROOT>
        </slickslider>

        <navigation>
            <ROOT>
                <TCEforms>
                    <sheetTitle>LLL:EXT:ws_slider/Resources/Private/Language/locallang.xlf:sheet.navigation</sheetTitle>
                </TCEforms>
                <type>array</type>
                <el>
                    <settings.js.accessibility>
                        <TCEforms>
                            <label>LLL:EXT:ws_slider/Resources/Private/Language/locallang.xlf:settings.slick.accessibility</label>
                            <config>
                                <type>select</type>
                                <renderType>selectSingleWithTypoScriptPlaceholder</renderType>
                                <typoscriptPath>plugin.tx_wsslider.settings.renderer.slickslider.accessibility</typoscriptPath>
                                <items type="array">
                                    <numIndex index="1" type="array">
                                        <numIndex index="0">LLL:EXT:ws_slider/Resources/Private/Language/locallang.xlf:yes</numIndex>
                                        <numIndex index="1">true</numIndex>
                                    </numIndex>
                                    <numIndex index="2" type="array">
                                        <numIndex index="0">LLL:EXT:ws_slider/Resources/Private/Language/locallang.xlf:no</numIndex>
                                        <numIndex index="1">false</numIndex>
                                    </numIndex>
                                </items>
                                <maxitems>1</maxitems>
                                <size>1</size>
                            </config>
                        </TCEforms>
                    </settings.js.accessibility>

                    <settings.js.arrows>
                        <TCEforms>
                            <label>LLL:EXT:ws_slider/Resources/Private/Language/locallang.xlf:settings.slick.arrows</label>
                            <config>
                                <type>select</type>
                                <renderType>selectSingleWithTypoScriptPlaceholder</renderType>
                                <typoscriptPath>plugin.tx_wsslider.settings.renderer.slickslider.arrows</typoscriptPath>
                                <items type="array">
                                    <numIndex index="1" type="array">
                                        <numIndex index="0">LLL:EXT:ws_slider/Resources/Private/Language/locallang.xlf:yes</numIndex>
                                        <numIndex index="1">true</numIndex>
                                    </numIndex>
                                    <numIndex index="2" type="array">
                                        <numIndex index="0">LLL:EXT:ws_slider/Resources/Private/Language/locallang.xlf:no</numIndex>
                                        <numIndex index="1">false</numIndex>
                                    </numIndex>
                                </items>
                                <maxitems>1</maxitems>
                                <size>1</size>
                            </config>
                        </TCEforms>
                    </settings.js.arrows>

                    <settings.js.asNavFor>
                        <TCEforms>
                            <exclude>1</exclude>
                            <label>LLL:EXT:ws_slider/Resources/Private/Language/locallang.xlf:settings.slick.asNavFor</label>
                            <config>
                                <type>input</type>
                                <renderType>inputWithTypoScriptPlaceholder</renderType>
                                <typoscriptPath>plugin.tx_wsslider.settings.renderer.slickslider.asNavFor</typoscriptPath>
                                <size>12</size>
                            </config>
                        </TCEforms>
                    </settings.js.asNavFor>

                    <settings.js.appendArrows>
                        <TCEforms>
                            <exclude>1</exclude>
                            <label>LLL:EXT:ws_slider/Resources/Private/Language/locallang.xlf:settings.slick.appendArrows</label>
                            <config>
                                <type>input</type>
                                <renderType>inputWithTypoScriptPlaceholder</renderType>
                                <typoscriptPath>plugin.tx_wsslider.settings.renderer.slickslider.appendArrows</typoscriptPath>
                                <size>12</size>
                            </config>
                        </TCEforms>
                    </settings.js.appendArrows>

                    <settings.js.appendDots>
                        <TCEforms>
                            <exclude>1</exclude>
                            <label>LLL:EXT:ws_slider/Resources/Private/Language/locallang.xlf:settings.slick.appendDots</label>
                            <config>
                                <type>input</type>
                                <renderType>inputWithTypoScriptPlaceholder</renderType>
                                <typoscriptPath>plugin.tx_wsslider.settings.renderer.slickslider.appendDots</typoscriptPath>
                                <size>12</size>
                            </config>
                        </TCEforms>
                    </settings.js.appendDots>

                    <settings.js.prevArrow>
                        <TCEforms>
                            <exclude>1</exclude>
                            <label>LLL:EXT:ws_slider/Resources/Private/Language/locallang.xlf:settings.slick.prevArrow</label>
                            <config>
                                <type>input</type>
                                <renderType>inputWithTypoScriptPlaceholder</renderType>
                                <typoscriptPath>plugin.tx_wsslider.settings.renderer.slickslider.prevArrow</typoscriptPath>
                                <size>12</size>
                            </config>
                        </TCEforms>
                    </settings.js.prevArrow>

                    <settings.js.nextArrow>
                        <TCEforms>
                            <exclude>1</exclude>
                            <label>LLL:EXT:ws_slider/Resources/Private/Language/locallang.xlf:settings.slick.nextArrow</label>
                            <config>
                                <type>input</type>
                                <renderType>inputWithTypoScriptPlaceholder</renderType>
                                <typoscriptPath>plugin.tx_wsslider.settings.renderer.slickslider.nextArrow</typoscriptPath>
                                <size>12</size>
                            </config>
                        </TCEforms>
                    </settings.js.nextArrow>

                    <settings.js.dots>
                        <TCEforms>
                            <label>LLL:EXT:ws_slider/Resources/Private/Language/locallang.xlf:settings.slick.dots</label>
                            <config>
                                <type>select</type>
                                <renderType>selectSingleWithTypoScriptPlaceholder</renderType>
                                <typoscriptPath>plugin.tx_wsslider.settings.renderer.slickslider.dots</typoscriptPath>
                                <items type="array">
                                    <numIndex index="1" type="array">
                                        <numIndex index="0">LLL:EXT:ws_slider/Resources/Private/Language/locallang.xlf:yes</numIndex>
                                        <numIndex index="1">true</numIndex>
                                    </numIndex>
                                    <numIndex index="2" type="array">
                                        <numIndex index="0">LLL:EXT:ws_slider/Resources/Private/Language/locallang.xlf:no</numIndex>
                                        <numIndex index="1">false</numIndex>
                                    </numIndex>
                                </items>
                                <maxitems>1</maxitems>
                                <size>1</size>
                            </config>
                        </TCEforms>
                    </settings.js.dots>
                </el>
            </ROOT>
        </navigation>

        <layout>
            <ROOT>
                <TCEforms>
                    <sheetTitle>LLL:EXT:ws_slider/Resources/Private/Language/locallang.xlf:sheet.layout</sheetTitle>
                </TCEforms>
                <type>array</type>
                <el>
                    <settings.js.adaptiveHeight>
                        <TCEforms>
                            <label>LLL:EXT:ws_slider/Resources/Private/Language/locallang.xlf:settings.common.autoHeight</label>
                            <config>
                                <type>select</type>
                                <renderType>selectSingleWithTypoScriptPlaceholder</renderType>
                                <typoscriptPath>plugin.tx_wsslider.settings.renderer.slickslider.adaptiveHeight</typoscriptPath>
                                <items type="array">
                                    <numIndex index="1" type="array">
                                        <numIndex index="0">LLL:EXT:ws_slider/Resources/Private/Language/locallang.xlf:yes</numIndex>
                                        <numIndex index="1">true</numIndex>
                                    </numIndex>
                                    <numIndex index="2" type="array">
                                        <numIndex index="0">LLL:EXT:ws_slider/Resources/Private/Language/locallang.xlf:no</numIndex>
                                        <numIndex index="1">false</numIndex>
                                    </numIndex>
                                </items>
                                <maxitems>1</maxitems>
                                <size>1</size>
                            </config>
                        </TCEforms>
                    </settings.js.adaptiveHeight>

                    <settings.js.centerMode>
                        <TCEforms>
                            <label>LLL:EXT:ws_slider/Resources/Private/Language/locallang.xlf:settings.slick.centerMode</label>
                            <config>
                                <type>select</type>
                                <renderType>selectSingleWithTypoScriptPlaceholder</renderType>
                                <typoscriptPath>plugin.tx_wsslider.settings.renderer.slickslider.centerMode</typoscriptPath>
                                <items type="array">
                                    <numIndex index="1" type="array">
                                        <numIndex index="0">LLL:EXT:ws_slider/Resources/Private/Language/locallang.xlf:yes</numIndex>
                                        <numIndex index="1">true</numIndex>
                                    </numIndex>
                                    <numIndex index="2" type="array">
                                        <numIndex index="0">LLL:EXT:ws_slider/Resources/Private/Language/locallang.xlf:no</numIndex>
                                        <numIndex index="1">false</numIndex>
                                    </numIndex>
                                </items>
                                <maxitems>1</maxitems>
                                <size>1</size>
                            </config>
                        </TCEforms>
                    </settings.js.centerMode>

                    <settings.js.centerPadding>
                        <TCEforms>
                            <label>LLL:EXT:ws_slider/Resources/Private/Language/locallang.xlf:settings.slick.centerPadding</label>
                            <config>
                                <type>input</type>
                                <renderType>inputWithTypoScriptPlaceholder</renderType>
                                <typoscriptPath>plugin.tx_wsslider.settings.renderer.slickslider.centerPadding</typoscriptPath>
                                <size>12</size>
                            </config>
                        </TCEforms>
                    </settings.js.centerPadding>


                </el>
            </ROOT>
        </layout>

        <dragNdrop>
            <ROOT>
                <TCEforms>
                    <sheetTitle>LLL:EXT:ws_slider/Resources/Private/Language/locallang.xlf:sheet.dragNdrop</sheetTitle>
                </TCEforms>
                <type>array</type>
                <el>

                </el>
            </ROOT>
        </dragNdrop>

        <animation>
            <ROOT>
                <TCEforms>
                    <sheetTitle>LLL:EXT:ws_slider/Resources/Private/Language/locallang.xlf:sheet.animation</sheetTitle>
                </TCEforms>
                <type>array</type>
                <el>
                    <settings.js.cssEase>
                        <TCEforms>
                            <label>LLL:EXT:ws_slider/Resources/Private/Language/locallang.xlf:settings.slick.cssEase</label>
                            <config>
                                <type>input</type>
                                <renderType>inputWithTypoScriptPlaceholder</renderType>
                                <typoscriptPath>plugin.tx_wsslider.settings.renderer.slickslider.cssEase</typoscriptPath>
                                <size>12</size>
                            </config>
                        </TCEforms>
                    </settings.js.cssEase>

                    <settings.js.customPaging>
                        <TCEforms>
                            <label>LLL:EXT:ws_slider/Resources/Private/Language/locallang.xlf:settings.slick.customPaging</label>
                            <config>
                                <type>input</type>
                                <renderType>inputWithTypoScriptPlaceholder</renderType>
                                <typoscriptPath>plugin.tx_wsslider.settings.renderer.slickslider.customPaging</typoscriptPath>
                                <size>12</size>
                            </config>
                        </TCEforms>
                    </settings.js.customPaging>
                </el>
            </ROOT>
        </animation>

        <advanced>
            <ROOT>
                <TCEforms>
                    <sheetTitle>LLL:EXT:ws_slider/Resources/Private/Language/locallang.xlf:sheet.advanced</sheetTitle>
                </TCEforms>
                <type>array</type>
                <el>

                </el>
            </ROOT>
        </advanced>

    </sheets>
</T3DataStructure>